maplapse/__init__.py
maplapse/maplapse.py
maplapse-0.0.6b2.dist-info/LICENSE
maplapse-0.0.6b2.dist-info/METADATA
maplapse-0.0.6b2.dist-info/WHEEL
maplapse-0.0.6b2.dist-info/top_level.txt
maplapse-0.0.6b2.dist-info/RECORD
