Metadata-Version: 2.1
Name: maplapse
Version: 0.0.6b2
Summary: A python library to create animated timelapse of maps
Home-page: https://github.com/souravbhadra/maplapse
Author: Sourav Bhadra
Author-email: sbhadra019@gmail.com
Classifier: Programming Language :: Python :: 3
Classifier: License :: OSI Approved :: MIT License
Classifier: Operating System :: OS Independent
Requires-Python: >=3.0
License-File: LICENSE
Requires-Dist: fiona (==1.8.21)
Requires-Dist: pyproj (==3.3.1)
Requires-Dist: rtree (==1.0.0)
Requires-Dist: shapely (==1.8.4)
Requires-Dist: geopandas (==0.11.1)
Requires-Dist: matplotlib (==3.5.3)
Requires-Dist: pandas (==1.4.3)
Requires-Dist: imageio (==2.21.1)
Requires-Dist: imageio-ffmpeg (==0.4.7)
Requires-Dist: tqdm (==4.64.0)
